brightspacepyclient.py
brightspacepyclient-0.0.4.dist-info/METADATA
brightspacepyclient-0.0.4.dist-info/WHEEL
brightspacepyclient-0.0.4.dist-info/RECORD
